lastuuid-0.4.2.dist-info/METADATA
lastuuid-0.4.2.dist-info/WHEEL
lastuuid/__init__.py
lastuuid/dummies.py
lastuuid/factories.py
lastuuid/lastuuid.pyi
lastuuid/lastuuid.pypy311-pp73-x86-linux-gnu.so
lastuuid/py.typed
lastuuid/utils.py
lastuuid-0.4.2.dist-info/RECORD
