Metadata-Version: 2.4
Name: lastuuid
Version: 0.4.2
Classifier: License :: OSI Approved :: MIT License
Classifier: Programming Language :: Python :: 3
Classifier: Programming Language :: Rust
Classifier: Topic :: Software Development :: Libraries :: Python Modules
Classifier: Typing :: Typed
Requires-Dist: furo>=2024.5.6 ; extra == 'docs'
Requires-Dist: linkify-it-py>=2.0.3,<3 ; extra == 'docs'
Requires-Dist: myst-parser>=3.0.0,<4 ; python_full_version < '3.10' and extra == 'docs'
Requires-Dist: myst-parser>=4.0.0,<5 ; python_full_version >= '3.10' and extra == 'docs'
Requires-Dist: sphinx>=7.0.1,<8 ; extra == 'docs'
Requires-Dist: sphinx-autodoc2>=0.5.0,<1 ; extra == 'docs'
Provides-Extra: docs
Summary: Fast UUIDv7 Compatible with standard library type, and utils.
Keywords: uuid,UUIDv7
Author-email: Guillaume Gauvrit <guillaume@gauvr.it>
License: MIT License
Requires-Python: >=3.9
Project-URL: Homepage, https://github.com/mardiros/lastuuid
Project-URL: Documentation, https://mardiros.github.io/lastuuid/
Project-URL: Repository, https://github.com/mardiros/lastuuid.git
Project-URL: Issues, https://github.com/mardiros/lastuuid/issues
Project-URL: Changelog, https://mardiros.github.io/lastuuid/changelog.html
